strong_json/__init__.py
strong_json/py.typed
strong_json/tests/__init__.py
strong_json/tests/test_strong_json.py
strong_json-1.0.11.dist-info/METADATA
strong_json-1.0.11.dist-info/WHEEL
strong_json-1.0.11.dist-info/top_level.txt
strong_json-1.0.11.dist-info/RECORD
