Metadata-Version: 2.1
Name: strong-json
Version: 1.0.11
Summary: JSON Decoder and Encoder with type information.
Home-page: https://github.com/piti118/strong-json
Author: Piti Ongmongkolkul
License: UNKNOWN
Keywords: json encoder decoder
Platform: UNKNOWN
Classifier: Development Status :: 4 - Beta
Classifier: Intended Audience :: Developers
Classifier: License :: OSI Approved :: MIT License
Classifier: Programming Language :: Python :: 3.7
Requires-Python: >=3.6
Provides-Extra: dev
Requires-Dist: pytest ; extra == 'dev'
Requires-Dist: numpy ; extra == 'dev'
Requires-Dist: pandas ; extra == 'dev'
Provides-Extra: test
Requires-Dist: pytest ; extra == 'test'
Requires-Dist: numpy ; extra == 'test'
Requires-Dist: pandas ; extra == 'test'
Requires-Dist: pytest-cov ; extra == 'test'
